{
  "date": "2026-07-04",
  "pairs": [
    {
      "pair": "黃金 vs 美元",
      "s1": "GLD",
      "s2": "UUP",
      "corr_20d": -0.562,
      "corr_60d": -0.64,
      "change_20d": 0.303,
      "anomaly": true
    },
    {
      "pair": "BTC vs 納指",
      "s1": "BTC-USD",
      "s2": "^IXIC",
      "corr_20d": -0.12,
      "corr_60d": 0.074,
      "change_20d": -0.489,
      "anomaly": true
    },
    {
      "pair": "S&P vs VIX",
      "s1": "^GSPC",
      "s2": "^VIX",
      "corr_20d": 0.234,
      "corr_60d": 0.16,
      "change_20d": 0.199,
      "anomaly": false
    },
    {
      "pair": "黃金 vs 殖利率",
      "s1": "GLD",
      "s2": "^TNX",
      "corr_20d": 0.173,
      "corr_60d": 0.02,
      "change_20d": 0.169,
      "anomaly": false
    },
    {
      "pair": "能源股 vs 油價",
      "s1": "XLE",
      "s2": "CL=F",
      "corr_20d": -0.254,
      "corr_60d": -0.135,
      "change_20d": -0.427,
      "anomaly": true
    },
    {
      "pair": "半導體 vs 納指",
      "s1": "SMH",
      "s2": "^IXIC",
      "corr_20d": 0.83,
      "corr_60d": 0.821,
      "change_20d": 0.013,
      "anomaly": false
    },
    {
      "pair": "BTC vs 黃金",
      "s1": "BTC-USD",
      "s2": "GLD",
      "corr_20d": 0.304,
      "corr_60d": 0.064,
      "change_20d": 0.282,
      "anomaly": false
    },
    {
      "pair": "科技 vs 能源",
      "s1": "XLK",
      "s2": "XLE",
      "corr_20d": -0.203,
      "corr_60d": -0.265,
      "change_20d": 0.265,
      "anomaly": false
    }
  ],
  "anomaly_count": 3
}