{
  "date": "2026-05-22",
  "updated_at": "2026-05-22 04:42",
  "total_scanned": 40,
  "watchlist_matches": 3,
  "status": "ok",
  "trades": [
    {
      "ticker": "JPM",
      "company": "JPMORGAN",
      "type": "未知",
      "title": "424B2 - JPMorgan Chase Financial Co. LLC (0001665650) (Filer)",
      "url": "https://www.sec.gov/Archives/edgar/data/1665650/000121390026060096/0001213900-26-060096-index.htm",
      "date": "2026-05-21T16:40:56-04:00",
      "summary": "Filed: 2026-05-21 AccNo: 0001213900-26-060096 Size: 2 MB"
    },
    {
      "ticker": "JPM",
      "company": "JPMORGAN",
      "type": "未知",
      "title": "424B2 - JPMORGAN CHASE & CO (0000019617) (Filer)",
      "url": "https://www.sec.gov/Archives/edgar/data/19617/000121390026060096/0001213900-26-060096-index.htm",
      "date": "2026-05-21T16:40:56-04:00",
      "summary": "Filed: 2026-05-21 AccNo: 0001213900-26-060096 Size: 2 MB"
    },
    {
      "ticker": "JPM",
      "company": "JPMORGAN",
      "type": "未知",
      "title": "424B2 - JPMorgan Chase Financial Co. LLC (0001665650) (Filer)",
      "url": "https://www.sec.gov/Archives/edgar/data/1665650/000191870426013840/0001918704-26-013840-index.htm",
      "date": "2026-05-21T16:40:37-04:00",
      "summary": "Filed: 2026-05-21 AccNo: 0001918704-26-013840 Size: 434 KB"
    }
  ]
}