{
  "mode": "intraday",
  "news": [
    {
      "title": "中東地緣政治衝突升級，伊朗局勢推升全球避險情緒與能源價格",
      "impact": "bearish",
      "source": "Bloomberg",
      "category": "Geo"
    },
    {
      "title": "聯準會維持利率於 3.50%-3.75% 區間，鮑爾釋放鷹派暫停訊號",
      "impact": "neutral",
      "source": "Reuters",
      "category": "Fed"
    },
    {
      "title": "美國 2 月 PPI 意外跳升 0.7%，批發端通膨壓力引發滯脹擔憂",
      "impact": "bearish",
      "source": "WSJ",
      "category": "Macro"
    },
    {
      "title": "非農就業人數意外減少 9.2 萬人，勞動力市場出現疲態",
      "impact": "bearish",
      "source": "CNBC",
      "category": "Macro"
    },
    {
      "title": "Uber 與 Nvidia 擴大無人駕駛合作，逆勢帶動 AI 應用板塊熱度",
      "impact": "bullish",
      "source": "TechCrunch",
      "category": "Earnings"
    }
  ],
  "macro_snapshot": {
    "fed_stance": "鷹派暫停；受戰爭引發的能源通膨影響，官員下修降息預期至全年僅一次。",
    "yield_10y": "4.29%（受避險資金與通膨預期雙重影響，維持高位）",
    "dxy": "98.5（地緣政治避險買盤推升美元走強）",
    "oil_wti": "90.2",
    "vix": "29.49（市場恐慌情緒顯著蔓延）"
  },
  "sector_rotation": {
    "strong": [
      "能源",
      "國防航太",
      "大宗商品"
    ],
    "weak": [
      "AI半導體",
      "高成長科技股",
      "非必需消費"
    ]
  },
  "key_drivers": [
    "地緣政治戰爭（伊朗衝突）引發的能源供給焦慮",
    "PPI 與 CPI 數據顯示通膨具有高度黏性，限縮降息空間",
    "經濟成長放緩跡象（NFP 負成長）引發市場對滯脹的擔憂"
  ],
  "market_tone": "市場陷入『避險模式 (Risk-off)』，投資者在戰爭通膨與經濟衰退風險之間掙扎。",
  "date": "2026-03-21",
  "fetched_at": "2026-03-21 03:00"
}
